pithermal/__init__.py
pithermal/meridian.py
pithermal/py.typed
pithermal-0.1.0a1.dist-info/WHEEL
pithermal-0.1.0a1.dist-info/METADATA
pithermal-0.1.0a1.dist-info/RECORD
