Metadata-Version: 2.3
Name: pithermal
Version: 0.1.0a1
Summary: Python library for thermal cameras compatible with Raspberry Pi
Requires-Dist: cmap>=0.6.2,<0.7.0
Requires-Dist: crcmod>=1.7,<2.0
Requires-Dist: gpiozero>=2.0.1,<3.0.0
Requires-Dist: numpy==2.0.2
Requires-Dist: pillow==11.2.1
Requires-Dist: rpi-gpio>=0.7.1,<0.8.0
Requires-Dist: smbus>=1.1.post2,<2.0
Requires-Dist: spidev>=3.8,<4.0
Requires-Python: >=3.9
